[
    {
      "id": 1,
      "name": "Buddy",
      "image": "https://plus.unsplash.com/premium_photo-1661503280224-a86d7ad2a574?q=80&w=1470&auto=format&fit=crop&ixlib=rb-4.0.3&ixid=M3wxMjA3fDB8MHxwaG90by1wYWdlfHx8fGVufDB8fHx8fA%3D%3D",
      "category": "Dog",
      "date": "2024-10-31",
      "status": "Published",
      "receiver_name": "John Doe",
      "receiver_image": "https://example.com/images/johndoe.jpg",
      "receiver_email": "john.doe@example.com",
      "location": "Chicago, USA",
      "owner_email": "mysuccessmission@gmail.com"
    },
    {
      "id": 2,
      "name": "Whiskers",
      "image": "https://images.unsplash.com/photo-1573865526739-10659fec78a5?q=80&w=1430&auto=format&fit=crop&ixlib=rb-4.0.3&ixid=M3wxMjA3fDB8MHxwaG90by1wYWdlfHx8fGVufDB8fHx8fA%3D%3D",
      "category": "Cat",
      "date": "2024-10-30",
      "status": "Adopted",
      "receiver_name": "Emma Brown",
      "receiver_image": "https://example.com/images/emmabrown.jpg",
      "receiver_email": "emma.brown@example.com",
      "location": "Chicago, USA",
       "owner_email": "mysuccessmission@gmail.com"
    },
    {
      "id": 3,
      "name": "Tweety",
      "image": "https://images.unsplash.com/photo-1470116073782-48ae2ccd8ffd?q=80&w=1412&auto=format&fit=crop&ixlib=rb-4.0.3&ixid=M3wxMjA3fDB8MHxwaG90by1wYWdlfHx8fGVufDB8fHx8fA%3D%3D",
      "category": "Bird",
      "date": "2024-10-29",
      "status": "Published",
      "receiver_name": "Robert Wilson",
      "receiver_image": "https://example.com/images/robertwilson.jpg",
      "receiver_email": "robert.wilson@example.com",
      "location": "Chicago, USA",
       "owner_email": "mysuccessmission@gmail.com"
    },
    {
      "id": 4,
      "name": "Fluffy",
      "image": "https://images.unsplash.com/photo-1478109214826-170faed7985c?q=80&w=1470&auto=format&fit=crop&ixlib=rb-4.0.3&ixid=M3wxMjA3fDB8MHxwaG90by1wYWdlfHx8fGVufDB8fHx8fA%3D%3D",
      "category": "Rabbit",
      "date": "2024-10-28",
      "status": "Adopted",
      "receiver_name": "Olivia Taylor",
      "receiver_image": "https://example.com/images/oliviataylor.jpg",
      "receiver_email": "olivia.taylor@example.com",
      "location": "Houston, USA",
      "owner_email": "mysuccessmission@gmail.com"
    },
    {
      "id": 5,
      "name": "Max",
      "image": "https://plus.unsplash.com/premium_photo-1710406095492-7e62eba19745?q=80&w=1502&auto=format&fit=crop&ixlib=rb-4.0.3&ixid=M3wxMjA3fDB8MHxwaG90by1wYWdlfHx8fGVufDB8fHx8fA%3D%3D",
      "category": "Dog",
      "date": "2024-10-27",
      "status": "Published",
      "receiver_name": "James Moore",
      "receiver_image": "https://example.com/images/jamesmoore.jpg",
      "receiver_email": "james.moore@example.com",
      "location": "Phoenix, USA",
       "owner_email": "mysuccessmission@gmail.com"
    },
    {
      "id": 6,
      "name": "Bella",
      "image": "https://images.unsplash.com/photo-1514888286974-6c03e2ca1dba?q=80&w=1443&auto=format&fit=crop&ixlib=rb-4.0.3&ixid=M3wxMjA3fDB8MHxwaG90by1wYWdlfHx8fGVufDB8fHx8fA%3D%3D",
      "category": "Cat",
      "date": "2024-10-26",
      "status": "Adopted",
      "receiver_image": "https://example.com/images/jamesmoore.jpg",
      "receiver_email": "james.moore@example.com",
      "location": "Phoenix, USA",
       "owner_email": "mysuccessmission@gmail.com"
    },
    {
      "id": 7,
      "name": "Polly",
      "image": "https://images.unsplash.com/photo-1470116073782-48ae2ccd8ffd?q=80&w=1412&auto=format&fit=crop&ixlib=rb-4.0.3&ixid=M3wxMjA3fDB8MHxwaG90by1wYWdlfHx8fGVufDB8fHx8fA%3D%3D",
      "category": "Bird",
      "date": "2024-10-25",
      "status": "Published",
      "receiver_image": "https://example.com/images/jamesmoore.jpg",
      "receiver_email": "james.moore@example.com",
      "location": "Phoenix, USA",
       "owner_email": "mysuccessmission@gmail.com"
    },
    {
      "id": 8,
      "name": "Snowball",
      "image": "https://images.unsplash.com/photo-1535241749838-299277b6305f?q=80&w=1492&auto=format&fit=crop&ixlib=rb-4.0.3&ixid=M3wxMjA3fDB8MHxwaG90by1wYWdlfHx8fGVufDB8fHx8fA%3D%3D",
      "category": "Rabbit",
      "date": "2024-10-24",
      "status": "Published",
      "receiver_image": "https://example.com/images/jamesmoore.jpg",
      "receiver_email": "james.moore@example.com",
      "location": "Phoenix, USA",
       "owner_email": "mysuccessmission@gmail.com"
    }
]
  